casbin/__init__.py
casbin/async_enforcer.py
casbin/async_internal_enforcer.py
casbin/async_management_enforcer.py
casbin/core_enforcer.py
casbin/distributed_enforcer.py
casbin/enforcer.py
casbin/fast_enforcer.py
casbin/frontend.py
casbin/internal_enforcer.py
casbin/management_enforcer.py
casbin/synced_enforcer.py
casbin/config/__init__.py
casbin/config/config.py
casbin/constant/__init__.py
casbin/constant/constants.py
casbin/effect/__init__.py
casbin/effect/default_effectors.py
casbin/effect/effector.py
casbin/model/__init__.py
casbin/model/assertion.py
casbin/model/function.py
casbin/model/model.py
casbin/model/model_fast.py
casbin/model/policy.py
casbin/model/policy_fast.py
casbin/model/policy_op.py
casbin/persist/__init__.py
casbin/persist/adapter.py
casbin/persist/adapter_filtered.py
casbin/persist/batch_adapter.py
casbin/persist/dispatcher.py
casbin/persist/update_adapter.py
casbin/persist/watcher.py
casbin/persist/watcher_ex.py
casbin/persist/watcher_update.py
casbin/persist/adapters/__init__.py
casbin/persist/adapters/adapter_filtered.py
casbin/persist/adapters/file_adapter.py
casbin/persist/adapters/filtered_file_adapter.py
casbin/persist/adapters/string_adapter.py
casbin/persist/adapters/update_adapter.py
casbin/persist/adapters/asyncio/__init__.py
casbin/persist/adapters/asyncio/adapter.py
casbin/persist/adapters/asyncio/adapter_filtered.py
casbin/persist/adapters/asyncio/batch_adapter.py
casbin/persist/adapters/asyncio/file_adapter.py
casbin/persist/adapters/asyncio/update_adapter.py
casbin/rbac/__init__.py
casbin/rbac/role_manager.py
casbin/rbac/default_role_manager/__init__.py
casbin/rbac/default_role_manager/role_manager.py
casbin/util/__init__.py
casbin/util/builtin_operators.py
casbin/util/expression.py
casbin/util/log.py
casbin/util/rwlock.py
casbin/util/util.py
node_modules/npm/node_modules/node-gyp/gyp/gyp_main.py
node_modules/npm/node_modules/node-gyp/gyp/test_gyp.py
node_modules/npm/node_modules/node-gyp/gyp/pylib/gyp/MSVSNew.py
casbin-1.41.0.dist-info/LICENSE
casbin-1.41.0.dist-info/METADATA
casbin-1.41.0.dist-info/WHEEL
casbin-1.41.0.dist-info/top_level.txt
casbin-1.41.0.dist-info/RECORD
