Metadata-Version: 2.2
Name: casbin
Version: 1.41.0
Summary: An authorization library that supports access control models like ACL, RBAC, ABAC in Python
Author-email: TechLee <techlee@qq.com>
License: Apache 2.0
Project-URL: Home-page, https://github.com/casbin/pycasbin
Keywords: casbin,acl,rbac,abac,auth,authz,authorization,access control,permission
Classifier: Programming Language :: Python :: 3.6
Classifier: Programming Language :: Python :: 3.7
Classifier: Programming Language :: Python :: 3.8
Classifier: Programming Language :: Python :: 3.9
Classifier: Programming Language :: Python :: 3.10
Classifier: Programming Language :: Python :: 3.11
Classifier: Programming Language :: Python :: 3.12
Classifier: License :: OSI Approved :: Apache Software License
Classifier: Operating System :: OS Independent
Requires-Python: >=3.3
License-File: LICENSE
Requires-Dist: simpleeval>=0.9.11
